{"week": 13, "team": "ARI", "stats": {"rec_yd": 21.32, "rec_tgt": 2.9, "rec_td": 0.14, "rec_fd": 2.13, "rec_5_9": 0.33, "rec_40p": 0.17, "rec_30_39": 0.17, "rec_20_29": 0.33, "rec_10_19": 0.5, "rec_0_4": 0.33, "rec": 1.66, "pts_std": 2.97, "pts_ppr": 4.63, "pts_half_ppr": 3.8, "gp": 1.0, "bonus_rec_te": 1.66}, "sport": "nfl", "season_type": "regular", "season": "2020", "player_id": "4741", "opponent": "LAR", "game_id": "202011301", "date": "2020-12-06", "company": "rotowire", "category": "proj"}