{"week": 6, "team": "ARI", "stats": {"sack_yd": 0.85, "pts_std": 0.6, "pts_ppr": 0.6, "pts_half_ppr": 0.6, "idp_tkl_solo": 4.94, "idp_tkl_loss": 0.45, "idp_tkl_ast": 3.29, "idp_tkl": 8.23, "idp_sack": 0.14, "idp_qb_hit": 0.34, "idp_pass_def": 0.34, "idp_int_ret_yd": 0.57, "idp_int": 0.11, "idp_fum_rec": 0.06, "idp_ff": 0.11, "gp": 1.0, "def_pr_yd": 0.57}, "sport": "nfl", "season_type": "regular", "season": "2020", "player_id": "2389", "opponent": "DAL", "game_id": "202010609", "date": "2020-10-19", "company": "rotowire", "category": "proj"}