{"week": 13, "team": "KC", "stats": {"yds_allow_300_349": 1.0, "yds_allow": 330.0, "tkl_solo": 35.0, "tkl_loss": 1.0, "tkl_ast": 23.0, "tkl": 58.0, "td": 1.0, "qb_hit": 4.0, "pts_std": 4.0, "pts_ppr": 4.0, "pts_half_ppr": 4.0, "pts_allow_14_20": 1.0, "pts_allow": 16.0, "penalty_yd": 44.0, "penalty": 5.0, "int": 2.0, "gp": 1.0, "fan_pts_allow_wr": 28.9, "fan_pts_allow_te": 12.4, "fan_pts_allow_rb": 17.8, "fan_pts_allow_qb": 12.94, "fan_pts_allow_k": 5.0, "fan_pts_allow": 77.04, "def_st_tkl_solo": 4.0, "def_pr_ypa": 5.0, "def_pr_yd": 5.0, "def_pr_lng": 5.0, "def_pr": 1.0, "def_pass_def": 4.0}, "sport": "nfl", "season_type": "regular", "season": "2020", "player_id": "KC", "opponent": "DEN", "game_id": "202011316", "date": "2020-12-06", "company": "sportradar", "category": "stat"}