{"week": 12, "team": "MIN", "stats": {"rush_yd": 0.56, "rush_fd": 0.06, "rush_att": 0.08, "rec_yd": 32.16, "rec_tgt": 4.3, "rec_td": 0.09, "rec_fd": 3.22, "rec_5_9": 0.61, "rec_40p": 0.31, "rec_30_39": 0.31, "rec_20_29": 0.61, "rec_10_19": 0.92, "rec_0_4": 0.61, "rec": 3.05, "pts_std": 3.81, "pts_ppr": 6.86, "pts_half_ppr": 5.34, "gp": 1.0, "bonus_rec_wr": 3.05}, "sport": "nfl", "season_type": "regular", "season": "2020", "player_id": "6088", "opponent": "CAR", "game_id": "202011220", "date": "2020-11-29", "company": "rotowire", "category": "proj"}