{"week": 9, "team": "BUF", "stats": {"def_pr_yd": 11.0, "yds_allow_400_449": 1.0, "def_kr_ypa": 40.0, "tkl": 55.0, "def_kr_lng": 60.0, "tkl_loss": 7.0, "fan_pts_allow_rb": 19.2, "pts_allow": 34.0, "sack_yd": 28.0, "penalty_yd": 70.0, "ff": 2.0, "def_kr_yd": 80.0, "fan_pts_allow_k": 14.0, "def_st_tkl_solo": 2.0, "int_ret_yd": 28.0, "gp": 1.0, "fan_pts_allow_qb": 36.0, "fan_pts_allow": 148.5, "def_pass_def": 6.0, "pts_allow_28_34": 1.0, "pts_half_ppr": 14.0, "fum_rec": 2.0, "qb_hit": 11.0, "def_pr": 1.0, "tkl_solo": 44.0, "int": 2.0, "def_pr_lng": 11.0, "tkl_ast": 11.0, "def_kr": 2.0, "def_pr_ypa": 11.0, "sack": 5.0, "fan_pts_allow_wr": 72.2, "td": 5.0, "fan_pts_allow_te": 7.1, "yds_allow": 419.0, "pts_ppr": 14.0, "penalty": 6.0, "pts_std": 14.0}, "sport": "nfl", "season_type": "regular", "season": "2020", "player_id": "BUF", "opponent": "SEA", "game_id": "202010904", "date": "2020-11-08", "company": "sportradar", "category": "stat"}