{"week": 17, "team": "BUF", "stats": {"yds_allow_300_349": 1.0, "yds_allow": 337.76, "tkl_loss": 3.68, "safe": 0.06, "sack": 2.27, "pts_std": 7.83, "pts_ppr": 7.83, "pts_half_ppr": 7.83, "pts_allow_14_20": 1.0, "pts_allow": 19.0, "pr_yd": 8.49, "pass_int_td": 0.17, "int": 0.85, "gp": 1.0, "fum_rec": 0.57, "ff": 1.13, "def_td": 0.23, "def_pr_yd": 45.3, "def_kr_yd": 36.81, "blk_kick": 0.06}, "sport": "nfl", "season_type": "regular", "season": "2020", "player_id": "BUF", "opponent": "MIA", "game_id": "202011704", "date": "2021-01-03", "company": "rotowire", "category": "proj"}