{"week": 17, "team": "JAX", "stats": {"yds_allow_350_399": 1.0, "yds_allow": 390.36, "tkl_loss": 3.08, "sack": 2.11, "pts_std": 5.76, "pts_ppr": 5.76, "pts_half_ppr": 5.76, "pts_allow_21_27": 1.0, "pts_allow": 27.75, "pr_yd": 19.95, "pass_int_td": 0.06, "int": 0.63, "gp": 1.0, "fum_rec": 0.46, "ff": 1.03, "def_td": 0.06, "def_pr_yd": 57.01, "def_kr_yd": 37.05, "blk_kick": 0.06}, "sport": "nfl", "season_type": "regular", "season": "2020", "player_id": "JAX", "opponent": "IND", "game_id": "202011714", "date": "2021-01-03", "company": "rotowire", "category": "proj"}