{"week": 5, "team": "BAL", "stats": {"def_pr_yd": 10.0, "def_kr_ypa": 30.0, "tkl_solo_misc": 1.0, "tkl": 66.0, "def_kr_lng": 30.0, "tkl_loss": 9.0, "fan_pts_allow_rb": 16.8, "pts_allow": 3.0, "sack_yd": 48.0, "penalty_yd": 25.0, "ff": 3.0, "def_kr_yd": 30.0, "pts_allow_1_6": 1.0, "fan_pts_allow_k": 3.0, "int_ret_yd": 12.0, "gp": 1.0, "fan_pts_allow_qb": 3.32, "fan_pts_allow": 46.62, "def_pass_def": 2.0, "pts_half_ppr": 29.0, "fum_rec": 2.0, "qb_hit": 15.0, "def_td": 1.0, "def_pr": 3.0, "tkl_solo": 43.0, "int": 1.0, "def_pr_lng": 10.0, "tkl_ast": 23.0, "def_kr": 1.0, "def_pr_ypa": 3.33, "sack": 7.0, "fan_pts_allow_wr": 19.3, "td": 3.0, "fum_ret_yd": 53.0, "fan_pts_allow_te": 4.2, "yds_allow": 205.0, "pts_ppr": 29.0, "penalty": 4.0, "yds_allow_200_299": 1.0, "pts_std": 29.0}, "sport": "nfl", "season_type": "regular", "season": "2020", "player_id": "BAL", "opponent": "CIN", "game_id": "202010503", "date": "2020-10-11", "company": "sportradar", "category": "stat"}