{"week": 3, "team": "MIN", "stats": {"rec_yd": 24.23, "rec_tgt": 3.3, "rec_td": 0.24, "rec_fd": 2.42, "rec_5_9": 0.52, "rec_40p": 0.26, "rec_30_39": 0.26, "rec_20_29": 0.52, "rec_10_19": 0.77, "rec_0_4": 0.52, "rec": 2.58, "pts_std": 3.86, "pts_ppr": 6.44, "pts_half_ppr": 5.15, "gp": 1.0, "bonus_rec_te": 2.58}, "sport": "nfl", "season_type": "regular", "season": "2020", "player_id": "943", "opponent": "TEN", "game_id": "202010320", "date": "2020-09-27", "company": "rotowire", "category": "proj"}