{"week": 15, "team": "NO", "stats": {"rush_yd": 41.93, "rush_td": 0.19, "rush_fd": 4.19, "rush_att": 9.1, "rec_yd": 9.97, "rec_tgt": 1.5, "rec_td": 0.04, "rec_fd": 1.0, "rec_5_9": 0.26, "rec_40p": 0.13, "rec_30_39": 0.13, "rec_20_29": 0.26, "rec_10_19": 0.39, "rec_0_4": 0.26, "rec": 1.3, "pts_std": 6.28, "pts_ppr": 7.58, "pts_half_ppr": 6.93, "gp": 1.0, "fum_lost": 0.05, "fum": 0.16, "bonus_rec_rb": 1.3}, "sport": "nfl", "season_type": "regular", "season": "2020", "player_id": "1476", "opponent": "KC", "game_id": "202011522", "date": "2020-12-20", "company": "rotowire", "category": "proj"}