{"week": 11, "team": "GB", "stats": {"rec_yd": 7.57, "rec_tgt": 1.0, "rec_td": 0.03, "rec_fd": 0.76, "rec_5_9": 0.14, "rec_40p": 0.07, "rec_30_39": 0.07, "rec_20_29": 0.14, "rec_10_19": 0.21, "rec_0_4": 0.14, "rec": 0.69, "pts_std": 0.94, "pts_ppr": 1.63, "pts_half_ppr": 1.28, "gp": 1.0, "bonus_rec_wr": 0.69}, "sport": "nfl", "season_type": "regular", "season": "2020", "player_id": "5323", "opponent": "IND", "game_id": "202011114", "date": "2020-11-22", "company": "rotowire", "category": "proj"}