{"week": 13, "team": "LV", "stats": {"rec_yd": 21.79, "rec_tgt": 2.5, "rec_td": 0.12, "rec_fd": 2.18, "rec_5_9": 0.33, "rec_40p": 0.16, "rec_30_39": 0.16, "rec_20_29": 0.33, "rec_10_19": 0.49, "rec_0_4": 0.33, "rec": 1.64, "pts_std": 2.92, "pts_ppr": 4.57, "pts_half_ppr": 3.75, "gp": 1.0, "bonus_rec_wr": 1.64}, "sport": "nfl", "season_type": "regular", "season": "2020", "player_id": "6870", "opponent": "NYJ", "game_id": "202011324", "date": "2020-12-06", "company": "rotowire", "category": "proj"}