{"week": 11, "team": "TB", "stats": {"rush_yd": 2.18, "rush_td": 0.09, "rush_fd": 0.22, "rush_att": 0.8, "pts_std": 20.64, "pts_ppr": 20.64, "pts_half_ppr": 20.64, "pass_yd": 292.66, "pass_td_40p": 0.27, "pass_td": 1.94, "pass_sack": 1.83, "pass_inc": 10.95, "pass_fd": 29.27, "pass_cmp_40p": 0.86, "pass_cmp": 26.05, "pass_att": 37.0, "pass_2pt": 0.12, "idp_int": 0.61, "gp": 1.0, "fum_lost": 0.21, "fum": 0.61, "cmp_pct": 70.41}, "sport": "nfl", "season_type": "regular", "season": "2020", "player_id": "167", "opponent": "LAR", "game_id": "202011133", "date": "2020-11-23", "company": "rotowire", "category": "proj"}