{"week": 1, "team": "CLE", "stats": {"yds_allow_400_449": 1.0, "yds_allow": 435.4, "tkl_loss": 2.44, "sack": 2.15, "pts_std": 5.95, "pts_ppr": 5.95, "pts_half_ppr": 5.95, "pts_allow_28_34": 1.0, "pts_allow": 31.75, "pr_yd": 7.32, "pass_int_td": 0.05, "int": 0.68, "gp": 1.0, "fum_rec": 0.44, "ff": 0.88, "def_td": 0.1, "def_pr_yd": 29.27, "def_kr_yd": 21.95, "blk_kick": 0.05}, "sport": "nfl", "season_type": "regular", "season": "2020", "player_id": "CLE", "opponent": "BAL", "game_id": "202010103", "date": "2020-09-13", "company": "rotowire", "category": "proj"}