{"week": 15, "team": "CIN", "stats": {"rush_yd": 14.84, "rush_td": 0.14, "rush_fd": 1.48, "rush_att": 2.8, "pts_std": 13.24, "pts_ppr": 13.24, "pts_half_ppr": 13.24, "pass_yd": 172.79, "pass_td": 0.73, "pass_sack": 3.93, "pass_int_td": 0.23, "pass_inc": 20.51, "pass_fd": 17.28, "pass_cmp_40p": 0.23, "pass_cmp": 15.79, "pass_att": 36.3, "pass_2pt": 0.23, "idp_int": 1.45, "gp": 1.0, "fum_lost": 0.69, "fum": 0.9, "cmp_pct": 43.51}, "sport": "nfl", "season_type": "regular", "season": "2020", "player_id": "5885", "opponent": "PIT", "game_id": "202011507", "date": "2020-12-21", "company": "rotowire", "category": "proj"}