{"week": 4, "team": "DAL", "stats": {"rush_yd": 16.3, "rush_td_40p": 0.03, "rush_td": 0.13, "rush_fd": 1.63, "rush_att": 3.1, "rush_40p": 0.03, "rec_yd": 7.78, "rec_tgt": 1.2, "rec_td": 0.04, "rec_fd": 0.78, "rec_5_9": 0.22, "rec_40p": 0.11, "rec_30_39": 0.11, "rec_20_29": 0.22, "rec_10_19": 0.33, "rec_0_4": 0.22, "rec": 1.09, "pts_std": 3.31, "pts_ppr": 4.4, "pts_half_ppr": 3.85, "gp": 1.0, "fum_lost": 0.03, "fum": 0.06, "def_kr_yd": 19.73, "bonus_rec_rb": 1.09}, "sport": "nfl", "season_type": "regular", "season": "2020", "player_id": "5967", "opponent": "CLE", "game_id": "202010409", "date": "2020-10-04", "company": "rotowire", "category": "proj"}