{"week": 7, "team": "ATL", "stats": {"rush_yd": 26.4, "rush_td": 0.16, "rush_fd": 2.64, "rush_att": 6.4, "rec_yd": 9.73, "rec_tgt": 2.0, "rec_fd": 0.97, "rec_5_9": 0.3, "rec_40p": 0.15, "rec_30_39": 0.15, "rec_20_29": 0.3, "rec_10_19": 0.45, "rec_0_4": 0.3, "rec": 1.51, "pts_std": 4.57, "pts_ppr": 6.08, "pts_half_ppr": 5.33, "gp": 1.0, "bonus_rec_rb": 1.51}, "sport": "nfl", "season_type": "regular", "season": "2020", "player_id": "4187", "opponent": "DET", "game_id": "202010702", "date": "2020-10-25", "company": "rotowire", "category": "proj"}