{"week": 7, "team": "ARI", "stats": {"rush_yd": 2.54, "rush_fd": 0.25, "rush_att": 0.44, "rec_yd": 26.26, "rec_tgt": 3.2, "rec_td_40p": 0.04, "rec_td": 0.31, "rec_fd": 2.63, "rec_5_9": 0.36, "rec_40p": 0.18, "rec_30_39": 0.18, "rec_20_29": 0.36, "rec_10_19": 0.54, "rec_0_4": 0.36, "rec": 1.8, "pts_std": 4.68, "pts_ppr": 6.48, "pts_half_ppr": 5.58, "gp": 1.0, "fum_lost": 0.02, "def_kr_yd": 20.93, "bonus_rec_wr": 1.8}, "sport": "nfl", "season_type": "regular", "season": "2020", "player_id": "5915", "opponent": "SEA", "game_id": "202010701", "date": "2020-10-25", "company": "rotowire", "category": "proj"}