{"week": 17, "team": "NYG", "stats": {"sack_yd": 0.36, "pts_std": 0.3, "pts_ppr": 0.3, "pts_half_ppr": 0.3, "idp_tkl_solo": 3.62, "idp_tkl_loss": 0.12, "idp_tkl_ast": 1.39, "idp_tkl": 5.01, "idp_sack": 0.06, "idp_qb_hit": 0.12, "idp_pass_def": 0.3, "idp_int_ret_yd": 0.9, "idp_int": 0.06, "idp_fum_rec": 0.06, "gp": 1.0, "def_pr_yd": 0.9}, "sport": "nfl", "season_type": "regular", "season": "2020", "player_id": "4056", "opponent": "DAL", "game_id": "202011723", "date": "2021-01-03", "company": "rotowire", "category": "proj"}