{"week": 14, "team": "JAX", "stats": {"pts_std": 0.44, "pts_ppr": 0.44, "pts_half_ppr": 0.44, "idp_tkl_solo": 3.61, "idp_tkl_loss": 0.25, "idp_tkl_ast": 1.62, "idp_tkl": 5.23, "idp_qb_hit": 0.06, "idp_pass_def": 0.19, "idp_int_ret_yd": 2.55, "idp_int": 0.12, "idp_fum_rec": 0.06, "idp_ff": 0.06, "gp": 1.0, "def_pr_yd": 2.55}, "sport": "nfl", "season_type": "regular", "season": "2020", "player_id": "3550", "opponent": "TEN", "game_id": "202011415", "date": "2020-12-13", "company": "rotowire", "category": "proj"}