{"week": 16, "team": "DAL", "stats": {"rec_yd": 15.93, "rec_tgt": 1.7, "rec_td": 0.06, "rec_fd": 1.59, "rec_5_9": 0.26, "rec_40p": 0.13, "rec_30_39": 0.13, "rec_20_29": 0.26, "rec_10_19": 0.39, "rec_0_4": 0.26, "rec": 1.31, "pts_std": 1.95, "pts_ppr": 3.26, "pts_half_ppr": 2.61, "gp": 1.0, "bonus_rec_wr": 1.31}, "sport": "nfl", "season_type": "regular", "season": "2020", "player_id": "4234", "opponent": "PHI", "game_id": "202011609", "date": "2020-12-27", "company": "rotowire", "category": "proj"}