{"week": 15, "team": "NO", "stats": {"rush_yd": 53.15, "rush_td_40p": 0.07, "rush_td": 0.55, "rush_fd": 5.32, "rush_att": 11.6, "rush_40p": 0.14, "rush_2pt": 0.07, "rec_yd": 55.75, "rec_tgt": 8.0, "rec_td_40p": 0.09, "rec_td": 0.21, "rec_fd": 5.57, "rec_5_9": 1.32, "rec_40p": 0.66, "rec_30_39": 0.66, "rec_2pt": 0.09, "rec_20_29": 1.32, "rec_10_19": 1.97, "rec_0_4": 1.32, "rec": 6.58, "pts_std": 15.15, "pts_ppr": 21.73, "pts_half_ppr": 18.44, "pr_yd": 2.4, "pr": 0.4, "gp": 1.0, "fum_lost": 0.16, "fum": 0.29, "bonus_rec_rb": 6.58}, "sport": "nfl", "season_type": "regular", "season": "2020", "player_id": "4035", "opponent": "KC", "game_id": "202011522", "date": "2020-12-20", "company": "rotowire", "category": "proj"}