{"week": 3, "team": "TEN", "stats": {"rush_yd": 8.53, "rush_fd": 0.85, "rush_att": 2.0, "rec_yd": 14.06, "rec_tgt": 2.1, "rec_td": 0.05, "rec_fd": 1.41, "rec_5_9": 0.36, "rec_40p": 0.18, "rec_30_39": 0.18, "rec_20_29": 0.36, "rec_10_19": 0.53, "rec_0_4": 0.36, "rec": 1.78, "pts_std": 2.56, "pts_ppr": 4.34, "pts_half_ppr": 3.45, "gp": 1.0, "bonus_rec_rb": 1.78}, "sport": "nfl", "season_type": "regular", "season": "2020", "player_id": "4219", "opponent": "MIN", "game_id": "202010320", "date": "2020-09-27", "company": "rotowire", "category": "proj"}