{"week": 5, "team": "NO", "stats": {"rush_yd": 7.08, "rush_td": 0.09, "rush_fd": 0.71, "rush_att": 1.3, "rec_yd": 4.98, "rec_tgt": 0.6, "rec_td": 0.1, "rec_fd": 0.5, "rec_5_9": 0.1, "rec_40p": 0.05, "rec_30_39": 0.05, "rec_20_29": 0.1, "rec_10_19": 0.15, "rec_0_4": 0.1, "rec": 0.5, "pts_std": 3.08, "pts_ppr": 3.58, "pts_half_ppr": 3.33, "pass_yd": 2.97, "pass_td": 0.16, "pass_sack": 0.13, "pass_inc": 0.09, "pass_fd": 0.3, "pass_cmp": 0.31, "pass_att": 0.4, "gp": 1.0, "def_kr_yd": 0.31, "cmp_pct": 78.1}, "sport": "nfl", "season_type": "regular", "season": "2020", "player_id": "4381", "opponent": "LAC", "game_id": "202010522", "date": "2020-10-12", "company": "rotowire", "category": "proj"}