{"week": 10, "team": "HOU", "stats": {"rush_yd": 65.57, "rush_td": 0.25, "rush_fd": 6.56, "rush_att": 14.2, "rec_yd": 28.34, "rec_tgt": 4.3, "rec_td": 0.18, "rec_fd": 2.83, "rec_5_9": 0.72, "rec_40p": 0.36, "rec_30_39": 0.36, "rec_20_29": 0.72, "rec_10_19": 1.09, "rec_0_4": 0.72, "rec": 3.62, "pts_std": 11.26, "pts_ppr": 14.88, "pts_half_ppr": 13.07, "gp": 1.0, "fum_lost": 0.18, "fum": 0.36, "bonus_rec_rb": 3.62}, "sport": "nfl", "season_type": "regular", "season": "2020", "player_id": "2382", "opponent": "CLE", "game_id": "202011008", "date": "2020-11-15", "company": "rotowire", "category": "proj"}