{"week": 16, "team": "NYJ", "stats": {"rush_yd": 40.42, "rush_td": 0.15, "rush_fd": 4.04, "rush_att": 12.3, "rec_yd": 5.26, "rec_tgt": 1.0, "rec_fd": 0.53, "rec_5_9": 0.15, "rec_40p": 0.07, "rec_30_39": 0.07, "rec_20_29": 0.15, "rec_10_19": 0.22, "rec_0_4": 0.15, "rec": 0.73, "pts_std": 5.31, "pts_ppr": 6.04, "pts_half_ppr": 5.67, "gp": 1.0, "fum": 0.14, "bonus_rec_rb": 0.73}, "sport": "nfl", "season_type": "regular", "season": "2020", "player_id": "232", "opponent": "CLE", "game_id": "202011624", "date": "2020-12-27", "company": "rotowire", "category": "proj"}