{"week": 15, "team": "GB", "stats": {"yds_allow_350_399": 1.0, "yds_allow": 359.83, "tkl_loss": 3.7, "sack": 2.63, "pts_std": 7.67, "pts_ppr": 7.67, "pts_half_ppr": 7.67, "pts_allow_21_27": 1.0, "pts_allow": 22.25, "pr_yd": 6.99, "pass_int_td": 0.14, "int": 0.86, "gp": 1.0, "fum_rec": 0.61, "ff": 1.12, "def_td": 0.14, "def_pr_yd": 41.92, "def_kr_yd": 34.93, "blk_kick": 0.07}, "sport": "nfl", "season_type": "regular", "season": "2020", "player_id": "GB", "opponent": "CAR", "game_id": "202011512", "date": "2020-12-19", "company": "rotowire", "category": "proj"}