{"week": 6, "team": "GB", "stats": {"yds_allow_350_399": 1.0, "yds_allow": 385.98, "tkl_loss": 3.01, "sack": 2.5, "pts_std": 6.98, "pts_ppr": 6.98, "pts_half_ppr": 6.98, "pts_allow_21_27": 1.0, "pts_allow": 25.25, "pr_yd": 5.68, "pass_int_td": 0.11, "int": 0.82, "gp": 1.0, "fum_rec": 0.58, "ff": 0.91, "def_td": 0.11, "def_pr_yd": 34.06, "def_kr_yd": 28.38, "blk_kick": 0.06}, "sport": "nfl", "season_type": "regular", "season": "2020", "player_id": "GB", "opponent": "TB", "game_id": "202010633", "date": "2020-10-18", "company": "rotowire", "category": "proj"}